intx_sdk/__init__.py
intx_sdk/base_response.py
intx_sdk/client.py
intx_sdk/client_services.py
intx_sdk/constants.py
intx_sdk/credentials.py
intx_sdk/enums.py
intx_sdk/main.py
intx_sdk/utils.py
intx_sdk/services/__init__.py
intx_sdk/services/model.py
intx_sdk/services/addressbook/__init__.py
intx_sdk/services/addressbook/get_address_book.py
intx_sdk/services/addressbook/service.py
intx_sdk/services/assets/__init__.py
intx_sdk/services/assets/get_asset_details.py
intx_sdk/services/assets/get_supported_networks.py
intx_sdk/services/assets/list_assets.py
intx_sdk/services/assets/service.py
intx_sdk/services/feerates/__init__.py
intx_sdk/services/feerates/list_fee_rate_tiers.py
intx_sdk/services/feerates/service.py
intx_sdk/services/index/__init__.py
intx_sdk/services/index/get_index_candles.py
intx_sdk/services/index/get_index_composition.py
intx_sdk/services/index/get_index_composition_history.py
intx_sdk/services/index/get_index_price.py
intx_sdk/services/index/service.py
intx_sdk/services/instruments/__init__.py
intx_sdk/services/instruments/get_aggregated_candles.py
intx_sdk/services/instruments/get_daily_trading_volumes.py
intx_sdk/services/instruments/get_historical_funding_rates.py
intx_sdk/services/instruments/get_instrument_details.py
intx_sdk/services/instruments/get_quote_per_instrument.py
intx_sdk/services/instruments/list_instruments.py
intx_sdk/services/instruments/service.py
intx_sdk/services/orders/__init__.py
intx_sdk/services/orders/cancel_order.py
intx_sdk/services/orders/cancel_orders.py
intx_sdk/services/orders/create_order.py
intx_sdk/services/orders/get_order_details.py
intx_sdk/services/orders/list_open_orders.py
intx_sdk/services/orders/modify_open_order.py
intx_sdk/services/orders/service.py
intx_sdk/services/portfolios/__init__.py
intx_sdk/services/portfolios/acquire_or_repay_loan.py
intx_sdk/services/portfolios/create_portfolio.py
intx_sdk/services/portfolios/enable_disable_auto_margin.py
intx_sdk_py-0.3.0.dist-info/licenses/LICENSE
intx_sdk_py-0.3.0.dist-info/METADATA
intx_sdk_py-0.3.0.dist-info/WHEEL
intx_sdk_py-0.3.0.dist-info/entry_points.txt
intx_sdk_py-0.3.0.dist-info/top_level.txt
intx_sdk_py-0.3.0.dist-info/RECORD
