Metadata-Version: 2.4
Name: intx-sdk-py
Version: 0.3.0
License-File: LICENSE
Requires-Dist: requests
Dynamic: license-file
Dynamic: requires-dist
